preciseLake/__init__.py
preciseLake/preciseLake.py
preciseLake-0.1.0.dist-info/LICENSE.txt
preciseLake-0.1.0.dist-info/METADATA
preciseLake-0.1.0.dist-info/WHEEL
preciseLake-0.1.0.dist-info/entry_points.txt
preciseLake-0.1.0.dist-info/top_level.txt
preciseLake-0.1.0.dist-info/RECORD
