Metadata-Version: 2.1
Name: preciseLake
Version: 0.1.0
Summary: A code health analyzer that also visualizes the structure.
Home-page: https://github.com/shreyashree00015/preciseLake
Author: Shreya Shree S
Author-email: shreyashree00015@gmail.com
Classifier: Programming Language :: Python :: 3
Classifier: License :: OSI Approved :: MIT License
Classifier: Operating System :: OS Independent
Requires-Python: >=3.6
License-File: LICENSE.txt
Requires-Dist: PyQt5
Requires-Dist: networkx
Requires-Dist: matplotlib
